event_reporter/__init__.py
event_reporter/classes.py
event_reporter-1.1.0.dist-info/LICENSE
event_reporter-1.1.0.dist-info/METADATA
event_reporter-1.1.0.dist-info/WHEEL
event_reporter-1.1.0.dist-info/develop_requires.txt
event_reporter-1.1.0.dist-info/tests_require.txt
event_reporter-1.1.0.dist-info/top_level.txt
event_reporter-1.1.0.dist-info/RECORD
