Metadata-Version: 2.1
Name: event-reporter
Version: 1.1.0
Summary: backend reporting via a worker/queue system
Home-page: https://github.com/e271828-/event-reporter
Author: e271828-
Author-email: e271828-@users.noreply.github.com
License: BSD
Platform: any
Classifier: Intended Audience :: Developers
Classifier: License :: OSI Approved :: BSD License
Classifier: Operating System :: OS Independent
Classifier: Programming Language :: Python
Classifier: Programming Language :: Python :: 3.4
Classifier: Programming Language :: Python :: 3.5
Classifier: Programming Language :: Python :: 3.6
Classifier: Programming Language :: Python :: 3.7
Classifier: Topic :: Software Development :: Libraries :: Python Modules
Requires-Dist: honeycomb-beeline (>=2.1.0)
Requires-Dist: google-measurement-protocol (>=1.0)
Requires-Dist: requests (>=2.22.0)
Requires-Dist: typing (>=3.6.0) ; python_version < "3.5"
